sqlalchemy_nested_mutable/__init__.py
sqlalchemy_nested_mutable/_compat.py
sqlalchemy_nested_mutable/_typing.py
sqlalchemy_nested_mutable/mutable.py
sqlalchemy_nested_mutable/testing/utils.py
sqlalchemy_nested_mutable/trackable.py
sqlalchemy_nested_mutable-0.2.0.dist-info/LICENSE
sqlalchemy_nested_mutable-0.2.0.dist-info/WHEEL
sqlalchemy_nested_mutable-0.2.0.dist-info/METADATA
sqlalchemy_nested_mutable-0.2.0.dist-info/RECORD
