Metadata-Version: 2.1
Name: sqlalchemy-nested-mutable
Version: 0.2.0
Summary: SQLAlchemy Nested Mutable Types.
Home-page: https://github.com/wonderbeyond/sqlalchemy-nested-mutable
License: MIT
Keywords: SQLAlchemy,Nested,Mutable,Types,JSON
Author: Wonder
Author-email: wonderbeyond@gmail.com
Requires-Python: >=3.8,<4.0
Classifier: Intended Audience :: Developers
Classifier: License :: OSI Approved :: MIT License
Classifier: Operating System :: OS Independent
Classifier: Programming Language :: Python :: 3
Classifier: Programming Language :: Python :: 3.8
Classifier: Programming Language :: Python :: 3.9
Classifier: Programming Language :: Python :: 3.10
Classifier: Programming Language :: Python :: 3.11
Classifier: Programming Language :: Python :: 3
Classifier: Topic :: Software Development :: Libraries :: Python Modules
Requires-Dist: psycopg2-binary (>=2.8,<3.0)
Requires-Dist: pydantic (>=1.10.0,<2.0.0)
Requires-Dist: sqlalchemy (>=2.0,<3.0)
Requires-Dist: typing-extensions (>=4.5.0,<5.0.0)
Project-URL: Documentation, https://github.com/wonderbeyond/sqlalchemy-nested-mutable
Project-URL: Repository, https://github.com/wonderbeyond/sqlalchemy-nested-mutable
